odoo10_addon_account_bank_statement_import_mt940_base-10.0.1.0.0.99.dev4-py2.7-nspkg.pth
odoo/addons/account_bank_statement_import_mt940_base/README.rst
odoo/addons/account_bank_statement_import_mt940_base/__init__.py
odoo/addons/account_bank_statement_import_mt940_base/__manifest__.py
odoo/addons/account_bank_statement_import_mt940_base/mt940.py
odoo/addons/account_bank_statement_import_mt940_base/i18n/account_bank_statement_import_mt940_base.pot
odoo/addons/account_bank_statement_import_mt940_base/static/description/icon.png
odoo/addons/account_bank_statement_import_mt940_base/test_files/test-ing.940
odoo/addons/account_bank_statement_import_mt940_base/test_files/test-rabo.swi
odoo/addons/account_bank_statement_import_mt940_base/test_files/test-sns.940
odoo/addons/account_bank_statement_import_mt940_base/test_files/test-wrong-file.940
odoo/addons/account_bank_statement_import_mt940_base/tests/__init__.py
odoo/addons/account_bank_statement_import_mt940_base/tests/test_import_bank_statement.py
odoo10_addon_account_bank_statement_import_mt940_base-10.0.1.0.0.99.dev4.dist-info/METADATA
odoo10_addon_account_bank_statement_import_mt940_base-10.0.1.0.0.99.dev4.dist-info/RECORD
odoo10_addon_account_bank_statement_import_mt940_base-10.0.1.0.0.99.dev4.dist-info/WHEEL
odoo10_addon_account_bank_statement_import_mt940_base-10.0.1.0.0.99.dev4.dist-info/namespace_packages.txt
odoo10_addon_account_bank_statement_import_mt940_base-10.0.1.0.0.99.dev4.dist-info/top_level.txt
