Metadata-Version: 2.1
Name: odoo10-addon-account-bank-statement-import-mt940-base
Version: 10.0.1.0.0.99.dev4
Summary: MT940 Bank Statements Import
Home-page: https://github.com/OCA/bank-statement-import
Author: Odoo Community Association (OCA), Therp BV
Author-email: support@odoo-community.org
License: AGPL-3
Platform: UNKNOWN
Classifier: Programming Language :: Python
Classifier: Framework :: Odoo
Classifier: License :: OSI Approved :: GNU Affero General Public License v3
Requires-Python: ~=2.7
Requires-Dist: odoo (<10.1dev,>=10.0)
